quippy/quippy.py
quippy-cli/quippy.py
quippy_cli-0.0.1.dist-info/LICENSE
quippy_cli-0.0.1.dist-info/METADATA
quippy_cli-0.0.1.dist-info/WHEEL
quippy_cli-0.0.1.dist-info/entry_points.txt
quippy_cli-0.0.1.dist-info/top_level.txt
quippy_cli-0.0.1.dist-info/RECORD
