Metadata-Version: 2.1
Name: quippy-cli
Version: 0.0.1
Summary: snippet manager for the CLI
Home-page: http://github.com/nk412/quippy
Author: Nagarjuna Kumarappan
Author-email: nagarjuna.412@gmail.com
License: MIT
Platform: UNKNOWN
Requires-Dist: pyfzf (>=0.2.1)
Requires-Dist: pyperclip (>=1.7.0)
Requires-Dist: PyYAML (>=5.3)
